win_cpusage/___init__.py
win_cpusage/cli.py
win_cpusage-1.0.0.dist-info/LICENSE
win_cpusage-1.0.0.dist-info/METADATA
win_cpusage-1.0.0.dist-info/WHEEL
win_cpusage-1.0.0.dist-info/top_level.txt
win_cpusage-1.0.0.dist-info/RECORD
