Metadata-Version: 2.1
Name: win-cpusage
Version: 1.0.0
Summary: A Python package to get CPU reports for any windows TEST.
Home-page: https://github.com/cpusagewin/cli-reporter
Author: Glenn C. Wilber
Author-email: nikhilksingh97@gmail.com
License: MIT
Platform: UNKNOWN
Classifier: License :: OSI Approved :: MIT License
Classifier: Programming Language :: Python :: 3
Classifier: Programming Language :: Python :: 3.7
Requires-Dist: psutil
